nearby/__init__.py
nearby_python-0.0.2.dist-info/licenses/LICENSE
nearby_python-0.0.2.dist-info/METADATA
nearby_python-0.0.2.dist-info/WHEEL
nearby_python-0.0.2.dist-info/top_level.txt
nearby_python-0.0.2.dist-info/RECORD
