Metadata-Version: 2.4
Name: nearby-python
Version: 0.0.2
Summary: Variability Analysis for EEG/BCI
Author: Simon Kojima
License: BSD 3-Clause License
Requires-Python: >=3.11
License-File: LICENSE
Requires-Dist: numpy
Requires-Dist: scipy
Requires-Dist: mne>=1.8
Requires-Dist: pandas
Dynamic: license-file
